odoo8_addon_hr_timesheet_no_closed_project_task-8.0.1.0.0.99.dev12-py2.7-nspkg.pth
odoo8_addon_hr_timesheet_no_closed_project_task-8.0.1.0.0.99.dev12.dist-info/METADATA
odoo8_addon_hr_timesheet_no_closed_project_task-8.0.1.0.0.99.dev12.dist-info/RECORD
odoo8_addon_hr_timesheet_no_closed_project_task-8.0.1.0.0.99.dev12.dist-info/WHEEL
odoo8_addon_hr_timesheet_no_closed_project_task-8.0.1.0.0.99.dev12.dist-info/namespace_packages.txt
odoo8_addon_hr_timesheet_no_closed_project_task-8.0.1.0.0.99.dev12.dist-info/top_level.txt
odoo_addons/hr_timesheet_no_closed_project_task/README.rst
odoo_addons/hr_timesheet_no_closed_project_task/__init__.py
odoo_addons/hr_timesheet_no_closed_project_task/__openerp__.py
odoo_addons/hr_timesheet_no_closed_project_task/i18n/es.po
odoo_addons/hr_timesheet_no_closed_project_task/i18n/fr.po
odoo_addons/hr_timesheet_no_closed_project_task/i18n/hr_timesheet_no_closed_project_task.pot
odoo_addons/hr_timesheet_no_closed_project_task/i18n/sl.po
odoo_addons/hr_timesheet_no_closed_project_task/models/__init__.py
odoo_addons/hr_timesheet_no_closed_project_task/models/hr_timesheet_line.py
odoo_addons/hr_timesheet_no_closed_project_task/models/project_task.py
odoo_addons/hr_timesheet_no_closed_project_task/security/ir.model.access.csv
odoo_addons/hr_timesheet_no_closed_project_task/static/description/icon.png
odoo_addons/hr_timesheet_no_closed_project_task/static/src/js/timesheet.js
odoo_addons/hr_timesheet_no_closed_project_task/views/hr_analytic_timesheet_view.xml
odoo_addons/hr_timesheet_no_closed_project_task/views/hr_timesheet_no_closed_project_task.xml
odoo_addons/hr_timesheet_no_closed_project_task/views/hr_timesheet_sheet_view.xml
odoo_addons/hr_timesheet_no_closed_project_task/views/project_task_view.xml
